clic/__init__.py
clic/main.py
clic/template/CMakeLists.txt
clic/template/readme.md
clic/template/solution.h
clic/template/test.cpp
clic-0.1.2.dist-info/LICENSE
clic-0.1.2.dist-info/METADATA
clic-0.1.2.dist-info/WHEEL
clic-0.1.2.dist-info/entry_points.txt
clic-0.1.2.dist-info/top_level.txt
clic-0.1.2.dist-info/RECORD
