Metadata-Version: 2.1
Name: clic
Version: 0.1.2
Summary: A c/c++ cli 
Home-page: https://github.com/AaronFlower/clic
Author: AaronFlower
Author-email: haojunzhan@gmail.com
License: UNKNOWN
Platform: UNKNOWN
Classifier: Programming Language :: Python :: 3
Classifier: License :: OSI Approved :: MIT License
Classifier: Operating System :: OS Independent
